CHANGELOG.md
LICENSE.txt
wagtail_sb_socialnetworks/__init__.py
wagtail_sb_socialnetworks/admin.py
wagtail_sb_socialnetworks/apps.py
wagtail_sb_socialnetworks/compat.py
wagtail_sb_socialnetworks/locale/es/LC_MESSAGES/django.po
wagtail_sb_socialnetworks/migrations/0001_initial.py
wagtail_sb_socialnetworks/migrations/0002_alter_socialnetwork_icon.py
wagtail_sb_socialnetworks/migrations/0003_rename_sitesettings_sitesocialnetworkprofile_site_settings_and_more.py
wagtail_sb_socialnetworks/migrations/__init__.py
wagtail_sb_socialnetworks/models.py
wagtail_sb_socialnetworks/tests.py
wagtail_sb_socialnetworks/version.py
wagtail_sb_socialnetworks/views.py
wagtail_sb_socialnetworks-0.7.0.dist-info/LICENSE.txt
wagtail_sb_socialnetworks-0.7.0.dist-info/METADATA
wagtail_sb_socialnetworks-0.7.0.dist-info/WHEEL
wagtail_sb_socialnetworks-0.7.0.dist-info/RECORD
